odoo/addons/l10n_it_website_portal_corrispettivi/README.rst
odoo/addons/l10n_it_website_portal_corrispettivi/__init__.py
odoo/addons/l10n_it_website_portal_corrispettivi/__manifest__.py
odoo/addons/l10n_it_website_portal_corrispettivi/controllers/__init__.py
odoo/addons/l10n_it_website_portal_corrispettivi/controllers/main.py
odoo/addons/l10n_it_website_portal_corrispettivi/i18n/it.po
odoo/addons/l10n_it_website_portal_corrispettivi/i18n/l10n_it_website_portal_corrispettivi.pot
odoo/addons/l10n_it_website_portal_corrispettivi/models/__init__.py
odoo/addons/l10n_it_website_portal_corrispettivi/models/res_partner.py
odoo/addons/l10n_it_website_portal_corrispettivi/readme/DESCRIPTION.rst
odoo/addons/l10n_it_website_portal_corrispettivi/static/description/icon.png
odoo/addons/l10n_it_website_portal_corrispettivi/static/description/index.html
odoo/addons/l10n_it_website_portal_corrispettivi/views/l10n_it_website_portal_corrispettivi_templates.xml
odoo12_addon_l10n_it_website_portal_corrispettivi-12.0.1.0.0.99.dev10.dist-info/METADATA
odoo12_addon_l10n_it_website_portal_corrispettivi-12.0.1.0.0.99.dev10.dist-info/WHEEL
odoo12_addon_l10n_it_website_portal_corrispettivi-12.0.1.0.0.99.dev10.dist-info/top_level.txt
odoo12_addon_l10n_it_website_portal_corrispettivi-12.0.1.0.0.99.dev10.dist-info/RECORD
