Metadata-Version: 2.1
Name: odoo12-addon-l10n-it-website-portal-corrispettivi
Version: 12.0.1.0.0.99.dev10
Summary: Aggiunge ricevuta o fattura come opzione nel profilo dell'utente portale
Home-page: https://github.com/OCA/l10n-italy/tree/12.0/l10n_it_website_portal_corrispettivi
Author: Odoo Community Association (OCA), TAKOBI
Author-email: support@odoo-community.org
License: AGPL-3
Platform: UNKNOWN
Classifier: Programming Language :: Python
Classifier: Framework :: Odoo
Classifier: Framework :: Odoo :: 12.0
Classifier: License :: OSI Approved :: GNU Affero General Public License v3
Requires-Python: >=3.5
Requires-Dist: odoo12-addon-l10n-it-corrispettivi
Requires-Dist: odoo <12.1dev,>=12.0a
